llm_foundry-0.22.0.dist-info/licenses/LICENSE
llmfoundry/__init__.py
llmfoundry/_version.py
llmfoundry/layers_registry.py
llmfoundry/registry.py
llmfoundry/algorithms/__init__.py
llmfoundry/callbacks/__init__.py
llmfoundry/callbacks/async_eval_callback.py
llmfoundry/callbacks/curriculum_learning_callback.py
llmfoundry/callbacks/dataset_swap_callback.py
llmfoundry/callbacks/env_logging_callback.py
llmfoundry/callbacks/eval_gauntlet_callback.py
llmfoundry/callbacks/eval_output_logging_callback.py
llmfoundry/callbacks/fdiff_callback.py
llmfoundry/callbacks/hf_checkpointer.py
llmfoundry/callbacks/kill_loss_spike_callback.py
llmfoundry/callbacks/log_mbmoe_tok_per_expert_callback.py
llmfoundry/callbacks/loss_perp_v_len_callback.py
llmfoundry/callbacks/monolithic_ckpt_callback.py
llmfoundry/callbacks/resumption_callbacks.py
llmfoundry/callbacks/run_timeout_callback.py
llmfoundry/callbacks/scheduled_gc_callback.py
llmfoundry/cli/__init__.py
llmfoundry/cli/cli.py
llmfoundry/cli/data_prep_cli.py
llmfoundry/cli/registry_cli.py
llmfoundry/command_utils/__init__.py
llmfoundry/command_utils/eval.py
llmfoundry/command_utils/train.py
llmfoundry/command_utils/data_prep/__init__.py
llmfoundry/command_utils/data_prep/convert_dataset_hf.py
llmfoundry/command_utils/data_prep/convert_dataset_json.py
llmfoundry/command_utils/data_prep/convert_delta_to_contrastive_mds.py
llmfoundry/command_utils/data_prep/convert_delta_to_json.py
llmfoundry/command_utils/data_prep/convert_finetuning_dataset.py
llmfoundry/command_utils/data_prep/convert_text_to_mds.py
llmfoundry/data/__init__.py
llmfoundry/data/data.py
llmfoundry/data/dataloader.py
llmfoundry/data/packing.py
llmfoundry/data/text_data.py
llmfoundry/data/utils.py
llmfoundry/data/contrastive_pairs/__init__.py
llmfoundry/data/contrastive_pairs/dataloader.py
llmfoundry/data/finetuning/__init__.py
llmfoundry/data/finetuning/collator.py
llmfoundry/data/finetuning/dataloader.py
llmfoundry/data/finetuning/tasks.py
llmfoundry/eval/__init__.py
llmfoundry/eval/datasets/__init__.py
llm_foundry-0.22.0.dist-info/METADATA
llm_foundry-0.22.0.dist-info/WHEEL
llm_foundry-0.22.0.dist-info/entry_points.txt
llm_foundry-0.22.0.dist-info/top_level.txt
llm_foundry-0.22.0.dist-info/RECORD
