Metadata-Version: 2.4
Name: llm-foundry
Version: 0.22.0
Summary: LLM Foundry
Home-page: https://github.com/mosaicml/llm-foundry/
Author: MosaicML
Author-email: team@mosaicml.com
Classifier: Programming Language :: Python :: 3
Classifier: Programming Language :: Python :: 3.10
Classifier: Programming Language :: Python :: 3.11
Classifier: Programming Language :: Python :: 3.12
Requires-Python: >=3.10
License-File: LICENSE
Requires-Dist: mosaicml[gcs,libcloud,mlflow,oci,wandb]<0.33,>=0.32.1
Requires-Dist: mlflow<3.0,>=2.14.1
Requires-Dist: accelerate<1.9,>=0.25
Requires-Dist: transformers<4.52,>=v4.51.0
Requires-Dist: mosaicml-streaming<0.13,>=0.12.0
Requires-Dist: torch<2.7.1,>=2.7.0
Requires-Dist: datasets<3.7,>=3.3.2
Requires-Dist: fsspec==2023.6.0
Requires-Dist: sentencepiece==0.2.0
Requires-Dist: einops==0.8.1
Requires-Dist: omegaconf<3,>=2.2.3
Requires-Dist: slack-sdk<4
Requires-Dist: mosaicml-cli<1,>=0.6.10
Requires-Dist: onnx==1.18.0
Requires-Dist: onnxruntime==1.22.0
Requires-Dist: boto3<2,>=1.21.45
Requires-Dist: huggingface-hub[hf_xet]<0.34,>=0.30.0
Requires-Dist: beautifulsoup4<5,>=4.12.2
Requires-Dist: tenacity<10,>=8.2.3
Requires-Dist: catalogue<3,>=2
Requires-Dist: typer<1
Requires-Dist: GitPython==3.1.44
Provides-Extra: dev
Requires-Dist: coverage[toml]==7.9.2; extra == "dev"
Requires-Dist: pre-commit<4,>=3.4.0; extra == "dev"
Requires-Dist: pytest<9,>=7.2.1; extra == "dev"
Requires-Dist: pytest_codeblocks<0.18,>=0.16.1; extra == "dev"
Requires-Dist: pytest-cov<7,>=4; extra == "dev"
Requires-Dist: pyright==1.1.256; extra == "dev"
Requires-Dist: toml<0.11,>=0.10.2; extra == "dev"
Requires-Dist: packaging<26,>=21; extra == "dev"
Requires-Dist: hf_transfer==0.1.9; extra == "dev"
Requires-Dist: tenacity<10,>=9; extra == "dev"
Provides-Extra: databricks
Requires-Dist: mosaicml[databricks]<0.33,>=0.32.1; extra == "databricks"
Requires-Dist: numpy<2; extra == "databricks"
Requires-Dist: databricks-sql-connector<4,>=3; extra == "databricks"
Requires-Dist: databricks-connect==14.1.0; extra == "databricks"
Requires-Dist: lz4<5,>=4; extra == "databricks"
Provides-Extra: tensorboard
Requires-Dist: mosaicml[tensorboard]<0.33,>=0.32.1; extra == "tensorboard"
Provides-Extra: gpu-flash2
Requires-Dist: flash-attn==2.7.4.post1; extra == "gpu-flash2"
Provides-Extra: gpu
Requires-Dist: flash-attn==2.7.4.post1; extra == "gpu"
Provides-Extra: peft
Requires-Dist: mosaicml[peft]<0.33,>=0.32.1; extra == "peft"
Provides-Extra: openai
Requires-Dist: openai<2.0,>=1.56.0; extra == "openai"
Requires-Dist: tiktoken<0.9.1,>=0.4; extra == "openai"
Provides-Extra: megablocks
Requires-Dist: megablocks<1.0; extra == "megablocks"
Requires-Dist: grouped-gemm==0.3.0; extra == "megablocks"
Provides-Extra: te
Requires-Dist: transformer-engine[pytorch]<2.0,>=1.13.0; extra == "te"
Provides-Extra: databricks-serverless
Requires-Dist: pre-commit<4,>=3.4.0; extra == "databricks-serverless"
Requires-Dist: pytest<9,>=7.2.1; extra == "databricks-serverless"
Requires-Dist: pytest-cov<7,>=4; extra == "databricks-serverless"
Requires-Dist: tenacity<10,>=9; extra == "databricks-serverless"
Requires-Dist: lz4<5,>=4; extra == "databricks-serverless"
Requires-Dist: toml<0.11,>=0.10.2; extra == "databricks-serverless"
Requires-Dist: mosaicml[databricks]<0.33,>=0.32.1; extra == "databricks-serverless"
Requires-Dist: pyright==1.1.256; extra == "databricks-serverless"
Requires-Dist: tiktoken<0.9.1,>=0.4; extra == "databricks-serverless"
Requires-Dist: coverage[toml]==7.9.2; extra == "databricks-serverless"
Requires-Dist: numpy<2; extra == "databricks-serverless"
Requires-Dist: openai<2.0,>=1.56.0; extra == "databricks-serverless"
Requires-Dist: mosaicml[peft]<0.33,>=0.32.1; extra == "databricks-serverless"
Requires-Dist: hf_transfer==0.1.9; extra == "databricks-serverless"
Requires-Dist: packaging<26,>=21; extra == "databricks-serverless"
Requires-Dist: databricks-sql-connector<4,>=3; extra == "databricks-serverless"
Requires-Dist: pytest_codeblocks<0.18,>=0.16.1; extra == "databricks-serverless"
Provides-Extra: all-cpu
Requires-Dist: pre-commit<4,>=3.4.0; extra == "all-cpu"
Requires-Dist: pytest<9,>=7.2.1; extra == "all-cpu"
Requires-Dist: pytest-cov<7,>=4; extra == "all-cpu"
Requires-Dist: tenacity<10,>=9; extra == "all-cpu"
Requires-Dist: databricks-connect==14.1.0; extra == "all-cpu"
Requires-Dist: toml<0.11,>=0.10.2; extra == "all-cpu"
Requires-Dist: mosaicml[databricks]<0.33,>=0.32.1; extra == "all-cpu"
Requires-Dist: pyright==1.1.256; extra == "all-cpu"
Requires-Dist: lz4<5,>=4; extra == "all-cpu"
Requires-Dist: tiktoken<0.9.1,>=0.4; extra == "all-cpu"
Requires-Dist: coverage[toml]==7.9.2; extra == "all-cpu"
Requires-Dist: numpy<2; extra == "all-cpu"
Requires-Dist: openai<2.0,>=1.56.0; extra == "all-cpu"
Requires-Dist: mosaicml[peft]<0.33,>=0.32.1; extra == "all-cpu"
Requires-Dist: hf_transfer==0.1.9; extra == "all-cpu"
Requires-Dist: packaging<26,>=21; extra == "all-cpu"
Requires-Dist: databricks-sql-connector<4,>=3; extra == "all-cpu"
Requires-Dist: pytest_codeblocks<0.18,>=0.16.1; extra == "all-cpu"
Provides-Extra: all
Requires-Dist: pre-commit<4,>=3.4.0; extra == "all"
Requires-Dist: mosaicml[tensorboard]<0.33,>=0.32.1; extra == "all"
Requires-Dist: lz4<5,>=4; extra == "all"
Requires-Dist: mosaicml[databricks]<0.33,>=0.32.1; extra == "all"
Requires-Dist: openai<2.0,>=1.56.0; extra == "all"
Requires-Dist: databricks-connect==14.1.0; extra == "all"
Requires-Dist: pytest-cov<7,>=4; extra == "all"
Requires-Dist: pyright==1.1.256; extra == "all"
Requires-Dist: flash-attn==2.7.4.post1; extra == "all"
Requires-Dist: grouped-gemm==0.3.0; extra == "all"
Requires-Dist: tenacity<10,>=9; extra == "all"
Requires-Dist: megablocks<1.0; extra == "all"
Requires-Dist: coverage[toml]==7.9.2; extra == "all"
Requires-Dist: numpy<2; extra == "all"
Requires-Dist: hf_transfer==0.1.9; extra == "all"
Requires-Dist: packaging<26,>=21; extra == "all"
Requires-Dist: pytest_codeblocks<0.18,>=0.16.1; extra == "all"
Requires-Dist: pytest<9,>=7.2.1; extra == "all"
Requires-Dist: toml<0.11,>=0.10.2; extra == "all"
Requires-Dist: tiktoken<0.9.1,>=0.4; extra == "all"
Requires-Dist: mosaicml[peft]<0.33,>=0.32.1; extra == "all"
Requires-Dist: databricks-sql-connector<4,>=3; extra == "all"
Provides-Extra: all-flash2
Requires-Dist: pre-commit<4,>=3.4.0; extra == "all-flash2"
Requires-Dist: mosaicml[tensorboard]<0.33,>=0.32.1; extra == "all-flash2"
Requires-Dist: lz4<5,>=4; extra == "all-flash2"
Requires-Dist: mosaicml[databricks]<0.33,>=0.32.1; extra == "all-flash2"
Requires-Dist: openai<2.0,>=1.56.0; extra == "all-flash2"
Requires-Dist: databricks-connect==14.1.0; extra == "all-flash2"
Requires-Dist: pytest-cov<7,>=4; extra == "all-flash2"
Requires-Dist: pyright==1.1.256; extra == "all-flash2"
Requires-Dist: flash-attn==2.7.4.post1; extra == "all-flash2"
Requires-Dist: grouped-gemm==0.3.0; extra == "all-flash2"
Requires-Dist: tenacity<10,>=9; extra == "all-flash2"
Requires-Dist: megablocks<1.0; extra == "all-flash2"
Requires-Dist: coverage[toml]==7.9.2; extra == "all-flash2"
Requires-Dist: numpy<2; extra == "all-flash2"
Requires-Dist: hf_transfer==0.1.9; extra == "all-flash2"
Requires-Dist: packaging<26,>=21; extra == "all-flash2"
Requires-Dist: pytest_codeblocks<0.18,>=0.16.1; extra == "all-flash2"
Requires-Dist: pytest<9,>=7.2.1; extra == "all-flash2"
Requires-Dist: toml<0.11,>=0.10.2; extra == "all-flash2"
Requires-Dist: tiktoken<0.9.1,>=0.4; extra == "all-flash2"
Requires-Dist: mosaicml[peft]<0.33,>=0.32.1; extra == "all-flash2"
Requires-Dist: databricks-sql-connector<4,>=3; extra == "all-flash2"
Dynamic: author
Dynamic: author-email
Dynamic: classifier
Dynamic: description
Dynamic: description-content-type
Dynamic: home-page
Dynamic: license-file
Dynamic: provides-extra
Dynamic: requires-dist
Dynamic: requires-python
Dynamic: summary
